Obfuscy/__init__.py
Obfuscy/main.py
obfuscy-0.0.1.dist-info/METADATA
obfuscy-0.0.1.dist-info/WHEEL
obfuscy-0.0.1.dist-info/licenses/LICENSE
obfuscy-0.0.1.dist-info/RECORD
