Metadata-Version: 2.1
Name: Obfuscy
Version: 0.0.1
Summary: A package to encrypt any sort of string or data. currently HEAVILY w.i.p.
Project-URL: Homepage, https://github.com/pypa/sampleproject
Project-URL: Bug Tracker, https://github.com/pypa/sampleproject/issues
Author-email: joploljojo3 <jorisblaauw12@gmail.com>
License-File: LICENSE
Classifier: License :: OSI Approved :: MIT License
Classifier: Operating System :: OS Independent
Classifier: Programming Language :: Python :: 3
Requires-Python: >=3.10
